MANIFEST.in
README.md
setup.py
ssouben_lib/__init__.py
ssouben_lib/core.py
ssouben_lib.egg-info/PKG-INFO
ssouben_lib.egg-info/SOURCES.txt
ssouben_lib.egg-info/dependency_links.txt
ssouben_lib.egg-info/entry_points.txt
ssouben_lib.egg-info/top_level.txt