Metadata-Version: 1.1
Name: ssouben-lib
Version: 0.0.3
Summary: Proclame la bonne parole de sieurs Sam et Max
Home-page: UNKNOWN
Author: Sam
Author-email: sam@gmail.com
License: WTFPL
Platform: UNKNOWN
Classifier: Programming Language :: Python
Classifier: Development Status :: 1 - Planning
Classifier: License :: OSI Approved
Classifier: Natural Language :: French
Classifier: Operating System :: OS Independent
Classifier: Programming Language :: Python :: 2.7
Classifier: Topic :: Communications
